Workbook

Sheet DREORÇ26
A1: Item | B1: Janeiro | C1: Real | D1: Fevereiro | E1: Real 2 | F1: Março | G1: Real 3 | H1: Abril | I1: Real 4 | J1: Maio | K1: Real 5 | L1: Junho | M1: Real 6 | N1: Julho | O1: Real 7 | P1: Agosto | Q1: Real 8 | R1: Setembro | S1: Real 9 | T1: Outubro | U1: Real 10 | V1: Novembro | W1: Real 11 | X1: Dezembro | Y1: Real 12 | Z1: TOTAL | AA1: Real 13
A2: (=) LUCRO LÍQUIDO | B2: =B4-(B19+B11) -> 0 | C2: =C4-(C19+C11) -> 0 | D2: =D4-(D19+D11) -> 0 | E2: =E4-(E19+E11) -> -1.31 | F2: =F4-(F19+F11) -> -120 | G2: =G4-(G19+G11) -> 0 | H2: =H4-(H19+H11) -> -120 | I2: =I4-(I19+I11) -> 0 | ... AA2: =AA4-(AA19+AA11) -> -1.31
A3: Margem Líquida
A4: RECEITA | B4: =SUM(B5:B9) -> 0 | C4: =SUM(C5:C9) -> 0 | D4: =SUM(D5:D9) -> 0 | E4: =SUM(E5:E9) -> 0 | F4: =SUM(F5:F9) -> 0 | G4: =SUM(G5:G9) -> 0 | H4: =SUM(H5:H9) -> 0 | I4: =SUM(I5:I9) -> 0 | ... AA4: =SUM(AA5:AA9) -> 0
A5: Pró-labore | C5: =IF(ISBLANK($A5), "", SUMIFS('Histórico26'!$C:$C, 'Histórico26'!$D:$D, $A5, 'Histórico26'!$A:$A, ">=01/01/2026", 'Histórico26'!$A:$A, "<=31/01/2026")) -> 0 | E5: =IF(ISBLANK($A5), "", SUMIFS('Histórico26'!$C:$C, 'Histórico26'!$D:$D, $A5, 'Histórico26'!$A:$A, ">=01/02/2026", 'Histórico26'!$A:$A, "<=28/02/2026")) -> 0 | G5: =IF(ISBLANK($A5), "", SUMIFS('Histórico26'!$C:$C, 'Histórico26'!$D:$D, $A5, 'Histórico26'!$A:$A, ">=01/03/2026", 'Histórico26'!$A:$A, "<=31/03/2026")) -> 0 | I5: =IF(ISBLANK($A5), "", SUMIFS('Histórico26'!$C:$C, 'Histórico26'!$D:$D, $A5, 'Histórico26'!$A:$A, ">=01/04/2026", 'Histórico26'!$A:$A, "<=30/04/2026")) -> 0 | K5: =IF(ISBLANK($A5), "", SUMIFS('Histórico26'!$C:$C, 'Histórico26'!$D:$D, $A5, 'Histórico26'!$A:$A, ">=01/05/2026", 'Histórico26'!$A:$A, "<=31/05/2026")) -> 0 | M5: =IF(ISBLANK($A5), "", SUMIFS('Histórico26'!$C:$C, 'Histórico26'!$D:$D, $A5, 'Histórico26'!$A:$A, ">=01/06/2026", 'Histórico26'!$A:$A, "<=30/06/2026")) -> 0 | O5: =IF(ISBLANK($A5), "", SUMIFS('Histórico26'!$C:$C, 'Histórico26'!$D:$D, $A5, 'Histórico26'!$A:$A, ">=01/07/2026", 'Histórico26'!$A:$A, "<=31/07/2026")) -> 0 | Q5: =IF(ISBLANK($A5), "", SUMIFS('Histórico26'!$C:$C, 'Histórico26'!$D:$D, $A5, 'Histórico26'!$A:$A, ">=01/08/2025", 'Histórico26'!$A:$A, "<=31/08/2025")) -> 0 | S5: =IF(ISBLANK($A5), "", SUMIFS('Histórico26'!$C:$C, 'Histórico26'!$D:$D, $A5, 'Histórico26'!$A:$A, ">=01/09/2025", 'Histórico26'!$A:$A, "<=31/09/2025")) -> 0 | U5: =IF(ISBLANK($A5), "", SUMIFS('Histórico26'!$C:$C, 'Histórico26'!$D:$D, $A5, 'Histórico26'!$A:$A, ">=01/10/2025", 'Histórico26'!$A:$A, "<=31/10/2025")) -> 0 | W5: =IF(ISBLANK($A5), "", SUMIFS('Histórico26'!$C:$C, 'Histórico26'!$D:$D, $A5, 'Histórico26'!$A:$A, ">=01/11/2025", 'Histórico26'!$A:$A, "<=30/11/2025")) -> 0 | Y5: =IF(ISBLANK($A5), "", SUMIFS('Histórico26'!$C:$C, 'Histórico26'!$D:$D, $A5, 'Histórico26'!$A:$A, ">=01/12/2025", 'Histórico26'!$A:$A, "<=31/12/2025")) -> 0 | Z5: =SUM(B5+D5+F5+H5+J5+L5+N5+P5+R5+T5+V5+X5) -> 0 | AA5: =SUM(C5,E5,G5,I5,K5,M5,O5,Q5,S5,U5,W5,Y5) -> 0
A6: Salário | C6: =IF(ISBLANK($A6), "", SUMIFS('Histórico26'!$C:$C, 'Histórico26'!$D:$D, $A6, 'Histórico26'!$A:$A, ">=01/01/2026", 'Histórico26'!$A:$A, "<=31/01/2026")) -> 0 | E6: =IF(ISBLANK($A6), "", SUMIFS('Histórico26'!$C:$C, 'Histórico26'!$D:$D, $A6, 'Histórico26'!$A:$A, ">=01/02/2026", 'Histórico26'!$A:$A, "<=28/02/2026")) -> 0 | G6: =IF(ISBLANK($A6), "", SUMIFS('Histórico26'!$C:$C, 'Histórico26'!$D:$D, $A6, 'Histórico26'!$A:$A, ">=01/03/2026", 'Histórico26'!$A:$A, "<=31/03/2026")) -> 0 | I6: =IF(ISBLANK($A6), "", SUMIFS('Histórico26'!$C:$C, 'Histórico26'!$D:$D, $A6, 'Histórico26'!$A:$A, ">=01/04/2026", 'Histórico26'!$A:$A, "<=30/04/2026")) -> 0 | K6: =IF(ISBLANK($A6), "", SUMIFS('Histórico26'!$C:$C, 'Histórico26'!$D:$D, $A6, 'Histórico26'!$A:$A, ">=01/05/2026", 'Histórico26'!$A:$A, "<=31/05/2026")) -> 0 | M6: =IF(ISBLANK($A6), "", SUMIFS('Histórico26'!$C:$C, 'Histórico26'!$D:$D, $A6, 'Histórico26'!$A:$A, ">=01/06/2026", 'Histórico26'!$A:$A, "<=30/06/2026")) -> 0 | O6: =IF(ISBLANK($A6), "", SUMIFS('Histórico26'!$C:$C, 'Histórico26'!$D:$D, $A6, 'Histórico26'!$A:$A, ">=01/07/2026", 'Histórico26'!$A:$A, "<=31/07/2026")) -> 0 | Q6: =IF(ISBLANK($A6), "", SUMIFS('Histórico26'!$C:$C, 'Histórico26'!$D:$D, $A6, 'Histórico26'!$A:$A, ">=01/08/2025", 'Histórico26'!$A:$A, "<=31/08/2025")) -> 0 | S6: =IF(ISBLANK($A6), "", SUMIFS('Histórico26'!$C:$C, 'Histórico26'!$D:$D, $A6, 'Histórico26'!$A:$A, ">=01/09/2025", 'Histórico26'!$A:$A, "<=31/09/2025")) -> 0 | U6: =IF(ISBLANK($A6), "", SUMIFS('Histórico26'!$C:$C, 'Histórico26'!$D:$D, $A6, 'Histórico26'!$A:$A, ">=01/10/2025", 'Histórico26'!$A:$A, "<=31/10/2025")) -> 0 | W6: =IF(ISBLANK($A6), "", SUMIFS('Histórico26'!$C:$C, 'Histórico26'!$D:$D, $A6, 'Histórico26'!$A:$A, ">=01/11/2025", 'Histórico26'!$A:$A, "<=30/11/2025")) -> 0 | Y6: =IF(ISBLANK($A6), "", SUMIFS('Histórico26'!$C:$C, 'Histórico26'!$D:$D, $A6, 'Histórico26'!$A:$A, ">=01/12/2025", 'Histórico26'!$A:$A, "<=31/12/2025")) -> 0 | Z6: =SUM(B6+D6+F6+H6+J6+L6+N6+P6+R6+T6+V6+X6) -> 0 | AA6: =SUM(C6,E6,G6,I6,K6,M6,O6,Q6,S6,U6,W6,Y6) -> 0
A7: Renda extra | C7: =IF(ISBLANK($A7), "", SUMIFS('Histórico26'!$C:$C, 'Histórico26'!$D:$D, $A7, 'Histórico26'!$A:$A, ">=01/01/2026", 'Histórico26'!$A:$A, "<=31/01/2026")) -> 0 | E7: =IF(ISBLANK($A7), "", SUMIFS('Histórico26'!$C:$C, 'Histórico26'!$D:$D, $A7, 'Histórico26'!$A:$A, ">=01/02/2026", 'Histórico26'!$A:$A, "<=28/02/2026")) -> 0 | G7: =IF(ISBLANK($A7), "", SUMIFS('Histórico26'!$C:$C, 'Histórico26'!$D:$D, $A7, 'Histórico26'!$A:$A, ">=01/03/2026", 'Histórico26'!$A:$A, "<=31/03/2026")) -> 0 | I7: =IF(ISBLANK($A7), "", SUMIFS('Histórico26'!$C:$C, 'Histórico26'!$D:$D, $A7, 'Histórico26'!$A:$A, ">=01/04/2026", 'Histórico26'!$A:$A, "<=30/04/2026")) -> 0 | K7: =IF(ISBLANK($A7), "", SUMIFS('Histórico26'!$C:$C, 'Histórico26'!$D:$D, $A7, 'Histórico26'!$A:$A, ">=01/05/2026", 'Histórico26'!$A:$A, "<=31/05/2026")) -> 0 | M7: =IF(ISBLANK($A7), "", SUMIFS('Histórico26'!$C:$C, 'Histórico26'!$D:$D, $A7, 'Histórico26'!$A:$A, ">=01/06/2026", 'Histórico26'!$A:$A, "<=30/06/2026")) -> 0 | O7: =IF(ISBLANK($A7), "", SUMIFS('Histórico26'!$C:$C, 'Histórico26'!$D:$D, $A7, 'Histórico26'!$A:$A, ">=01/07/2026", 'Histórico26'!$A:$A, "<=31/07/2026")) -> 0 | Q7: =IF(ISBLANK($A7), "", SUMIFS('Histórico26'!$C:$C, 'Histórico26'!$D:$D, $A7, 'Histórico26'!$A:$A, ">=01/08/2025", 'Histórico26'!$A:$A, "<=31/08/2025")) -> 0 | S7: =IF(ISBLANK($A7), "", SUMIFS('Histórico26'!$C:$C, 'Histórico26'!$D:$D, $A7, 'Histórico26'!$A:$A, ">=01/09/2025", 'Histórico26'!$A:$A, "<=31/09/2025")) -> 0 | U7: =IF(ISBLANK($A7), "", SUMIFS('Histórico26'!$C:$C, 'Histórico26'!$D:$D, $A7, 'Histórico26'!$A:$A, ">=01/10/2025", 'Histórico26'!$A:$A, "<=31/10/2025")) -> 0 | W7: =IF(ISBLANK($A7), "", SUMIFS('Histórico26'!$C:$C, 'Histórico26'!$D:$D, $A7, 'Histórico26'!$A:$A, ">=01/11/2025", 'Histórico26'!$A:$A, "<=30/11/2025")) -> 0 | Y7: =IF(ISBLANK($A7), "", SUMIFS('Histórico26'!$C:$C, 'Histórico26'!$D:$D, $A7, 'Histórico26'!$A:$A, ">=01/12/2025", 'Histórico26'!$A:$A, "<=31/12/2025")) -> 0 | Z7: =SUM(B7+D7+F7+H7+J7+L7+N7+P7+R7+T7+V7+X7) -> 0 | AA7: =SUM(C7,E7,G7,I7,K7,M7,O7,Q7,S7,U7,W7,Y7) -> 0
A8: Investimento (Entrada) | C8: =IF(ISBLANK($A8), "", SUMIFS('Histórico26'!$C:$C, 'Histórico26'!$D:$D, $A8, 'Histórico26'!$A:$A, ">=01/01/2026", 'Histórico26'!$A:$A, "<=31/01/2026")) -> 0 | E8: =IF(ISBLANK($A8), "", SUMIFS('Histórico26'!$C:$C, 'Histórico26'!$D:$D, $A8, 'Histórico26'!$A:$A, ">=01/02/2026", 'Histórico26'!$A:$A, "<=28/02/2026")) -> 0 | G8: =IF(ISBLANK($A8), "", SUMIFS('Histórico26'!$C:$C, 'Histórico26'!$D:$D, $A8, 'Histórico26'!$A:$A, ">=01/03/2026", 'Histórico26'!$A:$A, "<=31/03/2026")) -> 0 | I8: =IF(ISBLANK($A8), "", SUMIFS('Histórico26'!$C:$C, 'Histórico26'!$D:$D, $A8, 'Histórico26'!$A:$A, ">=01/04/2026", 'Histórico26'!$A:$A, "<=30/04/2026")) -> 0 | K8: =IF(ISBLANK($A8), "", SUMIFS('Histórico26'!$C:$C, 'Histórico26'!$D:$D, $A8, 'Histórico26'!$A:$A, ">=01/05/2026", 'Histórico26'!$A:$A, "<=31/05/2026")) -> 0 | M8: =IF(ISBLANK($A8), "", SUMIFS('Histórico26'!$C:$C, 'Histórico26'!$D:$D, $A8, 'Histórico26'!$A:$A, ">=01/06/2026", 'Histórico26'!$A:$A, "<=30/06/2026")) -> 0 | O8: =IF(ISBLANK($A8), "", SUMIFS('Histórico26'!$C:$C, 'Histórico26'!$D:$D, $A8, 'Histórico26'!$A:$A, ">=01/07/2026", 'Histórico26'!$A:$A, "<=31/07/2026")) -> 0 | Q8: =IF(ISBLANK($A8), "", SUMIFS('Histórico26'!$C:$C, 'Histórico26'!$D:$D, $A8, 'Histórico26'!$A:$A, ">=01/08/2025", 'Histórico26'!$A:$A, "<=31/08/2025")) -> 0 | S8: =IF(ISBLANK($A8), "", SUMIFS('Histórico26'!$C:$C, 'Histórico26'!$D:$D, $A8, 'Histórico26'!$A:$A, ">=01/09/2025", 'Histórico26'!$A:$A, "<=31/09/2025")) -> 0 | U8: =IF(ISBLANK($A8), "", SUMIFS('Histórico26'!$C:$C, 'Histórico26'!$D:$D, $A8, 'Histórico26'!$A:$A, ">=01/10/2025", 'Histórico26'!$A:$A, "<=31/10/2025")) -> 0 | W8: =IF(ISBLANK($A8), "", SUMIFS('Histórico26'!$C:$C, 'Histórico26'!$D:$D, $A8, 'Histórico26'!$A:$A, ">=01/11/2025", 'Histórico26'!$A:$A, "<=30/11/2025")) -> 0 | Y8: =IF(ISBLANK($A8), "", SUMIFS('Histórico26'!$C:$C, 'Histórico26'!$D:$D, $A8, 'Histórico26'!$A:$A, ">=01/12/2025", 'Histórico26'!$A:$A, "<=31/12/2025")) -> 0 | Z8: =SUM(B8+D8+F8+H8+J8+L8+N8+P8+R8+T8+V8+X8) -> 0 | AA8: =SUM(C8,E8,G8,I8,K8,M8,O8,Q8,S8,U8,W8,Y8) -> 0
A9: Outros (Entrada) | C9: =IF(ISBLANK($A9), "", SUMIFS('Histórico26'!$C:$C, 'Histórico26'!$D:$D, $A9, 'Histórico26'!$A:$A, ">=01/01/2026", 'Histórico26'!$A:$A, "<=31/01/2026")) -> 0 | E9: =IF(ISBLANK($A9), "", SUMIFS('Histórico26'!$C:$C, 'Histórico26'!$D:$D, $A9, 'Histórico26'!$A:$A, ">=01/02/2026", 'Histórico26'!$A:$A, "<=28/02/2026")) -> 0 | G9: =IF(ISBLANK($A9), "", SUMIFS('Histórico26'!$C:$C, 'Histórico26'!$D:$D, $A9, 'Histórico26'!$A:$A, ">=01/03/2026", 'Histórico26'!$A:$A, "<=31/03/2026")) -> 0 | I9: =IF(ISBLANK($A9), "", SUMIFS('Histórico26'!$C:$C, 'Histórico26'!$D:$D, $A9, 'Histórico26'!$A:$A, ">=01/04/2026", 'Histórico26'!$A:$A, "<=30/04/2026")) -> 0 | K9: =IF(ISBLANK($A9), "", SUMIFS('Histórico26'!$C:$C, 'Histórico26'!$D:$D, $A9, 'Histórico26'!$A:$A, ">=01/05/2026", 'Histórico26'!$A:$A, "<=31/05/2026")) -> 0 | M9: =IF(ISBLANK($A9), "", SUMIFS('Histórico26'!$C:$C, 'Histórico26'!$D:$D, $A9, 'Histórico26'!$A:$A, ">=01/06/2026", 'Histórico26'!$A:$A, "<=30/06/2026")) -> 0 | O9: =IF(ISBLANK($A9), "", SUMIFS('Histórico26'!$C:$C, 'Histórico26'!$D:$D, $A9, 'Histórico26'!$A:$A, ">=01/07/2026", 'Histórico26'!$A:$A, "<=31/07/2026")) -> 0 | Q9: =IF(ISBLANK($A9), "", SUMIFS('Histórico26'!$C:$C, 'Histórico26'!$D:$D, $A9, 'Histórico26'!$A:$A, ">=01/08/2025", 'Histórico26'!$A:$A, "<=31/08/2025")) -> 0 | S9: =IF(ISBLANK($A9), "", SUMIFS('Histórico26'!$C:$C, 'Histórico26'!$D:$D, $A9, 'Histórico26'!$A:$A, ">=01/09/2025", 'Histórico26'!$A:$A, "<=31/09/2025")) -> 0 | U9: =IF(ISBLANK($A9), "", SUMIFS('Histórico26'!$C:$C, 'Histórico26'!$D:$D, $A9, 'Histórico26'!$A:$A, ">=01/10/2025", 'Histórico26'!$A:$A, "<=31/10/2025")) -> 0 | W9: =IF(ISBLANK($A9), "", SUMIFS('Histórico26'!$C:$C, 'Histórico26'!$D:$D, $A9, 'Histórico26'!$A:$A, ">=01/11/2025", 'Histórico26'!$A:$A, "<=30/11/2025")) -> 0 | Y9: =IF(ISBLANK($A9), "", SUMIFS('Histórico26'!$C:$C, 'Histórico26'!$D:$D, $A9, 'Histórico26'!$A:$A, ">=01/12/2025", 'Histórico26'!$A:$A, "<=31/12/2025")) -> 0 | Z9: =SUM(B9+D9+F9+H9+J9+L9+N9+P9+R9+T9+V9+X9) -> 0 | AA9: =SUM(C9,E9,G9,I9,K9,M9,O9,Q9,S9,U9,W9,Y9) -> 0
A10: (=) RECEITA LÍQUIDA | B10: =B4-B9 -> 0 | C10: =C4-C9 -> 0 | D10: =D4-D9 -> 0 | E10: =E4-E9 -> 0 | F10: =F4-F9 -> 0 | G10: =G4-G9 -> 0 | H10: =H4-H9 -> 0 | I10: =I4-I9 -> 0 | ... AA10: =AA4-AA9 -> 0
A11: () CUSTOS | B11: =SUM(B12:B18) -> 0 | C11: =SUM(C12:C18) -> 0 | D11: =SUM(D12:D18) -> 0 | E11: =SUM(E12:E18) -> 0 | F11: =SUM(F12:F18) -> 120 | G11: =SUM(G12:G18) -> 0 | H11: =SUM(H12:H18) -> 120 | I11: =SUM(I12:I18) -> 0 | ... AA11: =SUM(AA12:AA18) -> 0
A12: Lanche | C12: =IF(ISBLANK($A12), "", SUMIFS('Histórico26'!$C:$C, 'Histórico26'!$D:$D, $A12, 'Histórico26'!$A:$A, ">=01/01/2026", 'Histórico26'!$A:$A, "<=31/01/2026")) -> 0 | E12: =IF(ISBLANK($A12), "", SUMIFS('Histórico26'!$C:$C, 'Histórico26'!$D:$D, $A12, 'Histórico26'!$A:$A, ">=01/02/2026", 'Histórico26'!$A:$A, "<=28/02/2026")) -> 0 | G12: =IF(ISBLANK($A12), "", SUMIFS('Histórico26'!$C:$C, 'Histórico26'!$D:$D, $A12, 'Histórico26'!$A:$A, ">=01/03/2026", 'Histórico26'!$A:$A, "<=31/03/2026")) -> 0 | I12: =IF(ISBLANK($A12), "", SUMIFS('Histórico26'!$C:$C, 'Histórico26'!$D:$D, $A12, 'Histórico26'!$A:$A, ">=01/04/2026", 'Histórico26'!$A:$A, "<=30/04/2026")) -> 0 | K12: =IF(ISBLANK($A12), "", SUMIFS('Histórico26'!$C:$C, 'Histórico26'!$D:$D, $A12, 'Histórico26'!$A:$A, ">=01/05/2026", 'Histórico26'!$A:$A, "<=31/05/2026")) -> 0 | M12: =IF(ISBLANK($A12), "", SUMIFS('Histórico26'!$C:$C, 'Histórico26'!$D:$D, $A12, 'Histórico26'!$A:$A, ">=01/06/2026", 'Histórico26'!$A:$A, "<=30/06/2026")) -> 0 | O12: =IF(ISBLANK($A12), "", SUMIFS('Histórico26'!$C:$C, 'Histórico26'!$D:$D, $A12, 'Histórico26'!$A:$A, ">=01/07/2026", 'Histórico26'!$A:$A, "<=31/07/2026")) -> 0 | Q12: =IF(ISBLANK($A12), "", SUMIFS('Histórico26'!$C:$C, 'Histórico26'!$D:$D, $A12, 'Histórico26'!$A:$A, ">=01/08/2025", 'Histórico26'!$A:$A, "<=31/08/2025")) -> 0 | S12: =IF(ISBLANK($A12), "", SUMIFS('Histórico26'!$C:$C, 'Histórico26'!$D:$D, $A12, 'Histórico26'!$A:$A, ">=01/09/2025", 'Histórico26'!$A:$A, "<=31/09/2025")) -> 0 | U12: =IF(ISBLANK($A12), "", SUMIFS('Histórico26'!$C:$C, 'Histórico26'!$D:$D, $A12, 'Histórico26'!$A:$A, ">=01/10/2025", 'Histórico26'!$A:$A, "<=31/10/2025")) -> 0 | W12: =IF(ISBLANK($A12), "", SUMIFS('Histórico26'!$C:$C, 'Histórico26'!$D:$D, $A12, 'Histórico26'!$A:$A, ">=01/11/2025", 'Histórico26'!$A:$A, "<=30/11/2025")) -> 0 | Y12: =IF(ISBLANK($A12), "", SUMIFS('Histórico26'!$C:$C, 'Histórico26'!$D:$D, $A12, 'Histórico26'!$A:$A, ">=01/12/2025", 'Histórico26'!$A:$A, "<=31/12/2025")) -> 0 | Z12: =SUM(B12+D12+F12+H12+J12+L12+N12+P12+R12+T12+V12+X12) -> 0 | AA12: =SUM(C12,E12,G12,I12,K12,M12,O12,Q12,S12,U12,W12,Y12) -> 0
A13: Roupa | C13: =IF(ISBLANK($A13), "", SUMIFS('Histórico26'!$C:$C, 'Histórico26'!$D:$D, $A13, 'Histórico26'!$A:$A, ">=01/01/2026", 'Histórico26'!$A:$A, "<=31/01/2026")) -> 0 | E13: =IF(ISBLANK($A13), "", SUMIFS('Histórico26'!$C:$C, 'Histórico26'!$D:$D, $A13, 'Histórico26'!$A:$A, ">=01/02/2026", 'Histórico26'!$A:$A, "<=28/02/2026")) -> 0 | G13: =IF(ISBLANK($A13), "", SUMIFS('Histórico26'!$C:$C, 'Histórico26'!$D:$D, $A13, 'Histórico26'!$A:$A, ">=01/03/2026", 'Histórico26'!$A:$A, "<=31/03/2026")) -> 0 | I13: =IF(ISBLANK($A13), "", SUMIFS('Histórico26'!$C:$C, 'Histórico26'!$D:$D, $A13, 'Histórico26'!$A:$A, ">=01/04/2026", 'Histórico26'!$A:$A, "<=30/04/2026")) -> 0 | K13: =IF(ISBLANK($A13), "", SUMIFS('Histórico26'!$C:$C, 'Histórico26'!$D:$D, $A13, 'Histórico26'!$A:$A, ">=01/05/2026", 'Histórico26'!$A:$A, "<=31/05/2026")) -> 0 | M13: =IF(ISBLANK($A13), "", SUMIFS('Histórico26'!$C:$C, 'Histórico26'!$D:$D, $A13, 'Histórico26'!$A:$A, ">=01/06/2026", 'Histórico26'!$A:$A, "<=30/06/2026")) -> 0 | O13: =IF(ISBLANK($A13), "", SUMIFS('Histórico26'!$C:$C, 'Histórico26'!$D:$D, $A13, 'Histórico26'!$A:$A, ">=01/07/2026", 'Histórico26'!$A:$A, "<=31/07/2026")) -> 0 | Q13: =IF(ISBLANK($A13), "", SUMIFS('Histórico26'!$C:$C, 'Histórico26'!$D:$D, $A13, 'Histórico26'!$A:$A, ">=01/08/2025", 'Histórico26'!$A:$A, "<=31/08/2025")) -> 0 | S13: =IF(ISBLANK($A13), "", SUMIFS('Histórico26'!$C:$C, 'Histórico26'!$D:$D, $A13, 'Histórico26'!$A:$A, ">=01/09/2025", 'Histórico26'!$A:$A, "<=31/09/2025")) -> 0 | U13: =IF(ISBLANK($A13), "", SUMIFS('Histórico26'!$C:$C, 'Histórico26'!$D:$D, $A13, 'Histórico26'!$A:$A, ">=01/10/2025", 'Histórico26'!$A:$A, "<=31/10/2025")) -> 0 | W13: =IF(ISBLANK($A13), "", SUMIFS('Histórico26'!$C:$C, 'Histórico26'!$D:$D, $A13, 'Histórico26'!$A:$A, ">=01/11/2025", 'Histórico26'!$A:$A, "<=30/11/2025")) -> 0 | Y13: =IF(ISBLANK($A13), "", SUMIFS('Histórico26'!$C:$C, 'Histórico26'!$D:$D, $A13, 'Histórico26'!$A:$A, ">=01/12/2025", 'Histórico26'!$A:$A, "<=31/12/2025")) -> 0 | Z13: =SUM(B13+D13+F13+H13+J13+L13+N13+P13+R13+T13+V13+X13) -> 0 | AA13: =SUM(C13,E13,G13,I13,K13,M13,O13,Q13,S13,U13,W13,Y13) -> 0
A14: Transporte | C14: =IF(ISBLANK($A14), "", SUMIFS('Histórico26'!$C:$C, 'Histórico26'!$D:$D, $A14, 'Histórico26'!$A:$A, ">=01/01/2026", 'Histórico26'!$A:$A, "<=31/01/2026")) -> 0 | E14: =IF(ISBLANK($A14), "", SUMIFS('Histórico26'!$C:$C, 'Histórico26'!$D:$D, $A14, 'Histórico26'!$A:$A, ">=01/02/2026", 'Histórico26'!$A:$A, "<=28/02/2026")) -> 0 | G14: =IF(ISBLANK($A14), "", SUMIFS('Histórico26'!$C:$C, 'Histórico26'!$D:$D, $A14, 'Histórico26'!$A:$A, ">=01/03/2026", 'Histórico26'!$A:$A, "<=31/03/2026")) -> 0 | I14: =IF(ISBLANK($A14), "", SUMIFS('Histórico26'!$C:$C, 'Histórico26'!$D:$D, $A14, 'Histórico26'!$A:$A, ">=01/04/2026", 'Histórico26'!$A:$A, "<=30/04/2026")) -> 0 | K14: =IF(ISBLANK($A14), "", SUMIFS('Histórico26'!$C:$C, 'Histórico26'!$D:$D, $A14, 'Histórico26'!$A:$A, ">=01/05/2026", 'Histórico26'!$A:$A, "<=31/05/2026")) -> 0 | M14: =IF(ISBLANK($A14), "", SUMIFS('Histórico26'!$C:$C, 'Histórico26'!$D:$D, $A14, 'Histórico26'!$A:$A, ">=01/06/2026", 'Histórico26'!$A:$A, "<=30/06/2026")) -> 0 | O14: =IF(ISBLANK($A14), "", SUMIFS('Histórico26'!$C:$C, 'Histórico26'!$D:$D, $A14, 'Histórico26'!$A:$A, ">=01/07/2026", 'Histórico26'!$A:$A, "<=31/07/2026")) -> 0 | Q14: =IF(ISBLANK($A14), "", SUMIFS('Histórico26'!$C:$C, 'Histórico26'!$D:$D, $A14, 'Histórico26'!$A:$A, ">=01/08/2025", 'Histórico26'!$A:$A, "<=31/08/2025")) -> 0 | S14: =IF(ISBLANK($A14), "", SUMIFS('Histórico26'!$C:$C, 'Histórico26'!$D:$D, $A14, 'Histórico26'!$A:$A, ">=01/09/2025", 'Histórico26'!$A:$A, "<=31/09/2025")) -> 0 | U14: =IF(ISBLANK($A14), "", SUMIFS('Histórico26'!$C:$C, 'Histórico26'!$D:$D, $A14, 'Histórico26'!$A:$A, ">=01/10/2025", 'Histórico26'!$A:$A, "<=31/10/2025")) -> 0 | W14: =IF(ISBLANK($A14), "", SUMIFS('Histórico26'!$C:$C, 'Histórico26'!$D:$D, $A14, 'Histórico26'!$A:$A, ">=01/11/2025", 'Histórico26'!$A:$A, "<=30/11/2025")) -> 0 | Y14: =IF(ISBLANK($A14), "", SUMIFS('Histórico26'!$C:$C, 'Histórico26'!$D:$D, $A14, 'Histórico26'!$A:$A, ">=01/12/2025", 'Histórico26'!$A:$A, "<=31/12/2025")) -> 0 | Z14: =SUM(B14+D14+F14+H14+J14+L14+N14+P14+R14+T14+V14+X14) -> 0 | AA14: =SUM(C14,E14,G14,I14,K14,M14,O14,Q14,S14,U14,W14,Y14) -> 0
A15: Igreja | C15: =IF(ISBLANK($A15), "", SUMIFS('Histórico26'!$C:$C, 'Histórico26'!$D:$D, $A15, 'Histórico26'!$A:$A, ">=01/01/2026", 'Histórico26'!$A:$A, "<=31/01/2026")) -> 0 | E15: =IF(ISBLANK($A15), "", SUMIFS('Histórico26'!$C:$C, 'Histórico26'!$D:$D, $A15, 'Histórico26'!$A:$A, ">=01/02/2026", 'Histórico26'!$A:$A, "<=28/02/2026")) -> 0 | G15: =IF(ISBLANK($A15), "", SUMIFS('Histórico26'!$C:$C, 'Histórico26'!$D:$D, $A15, 'Histórico26'!$A:$A, ">=01/03/2026", 'Histórico26'!$A:$A, "<=31/03/2026")) -> 0 | I15: =IF(ISBLANK($A15), "", SUMIFS('Histórico26'!$C:$C, 'Histórico26'!$D:$D, $A15, 'Histórico26'!$A:$A, ">=01/04/2026", 'Histórico26'!$A:$A, "<=30/04/2026")) -> 0 | K15: =IF(ISBLANK($A15), "", SUMIFS('Histórico26'!$C:$C, 'Histórico26'!$D:$D, $A15, 'Histórico26'!$A:$A, ">=01/05/2026", 'Histórico26'!$A:$A, "<=31/05/2026")) -> 0 | M15: =IF(ISBLANK($A15), "", SUMIFS('Histórico26'!$C:$C, 'Histórico26'!$D:$D, $A15, 'Histórico26'!$A:$A, ">=01/06/2026", 'Histórico26'!$A:$A, "<=30/06/2026")) -> 0 | O15: =IF(ISBLANK($A15), "", SUMIFS('Histórico26'!$C:$C, 'Histórico26'!$D:$D, $A15, 'Histórico26'!$A:$A, ">=01/07/2026", 'Histórico26'!$A:$A, "<=31/07/2026")) -> 0 | Q15: =IF(ISBLANK($A15), "", SUMIFS('Histórico26'!$C:$C, 'Histórico26'!$D:$D, $A15, 'Histórico26'!$A:$A, ">=01/08/2025", 'Histórico26'!$A:$A, "<=31/08/2025")) -> 0 | S15: =IF(ISBLANK($A15), "", SUMIFS('Histórico26'!$C:$C, 'Histórico26'!$D:$D, $A15, 'Histórico26'!$A:$A, ">=01/09/2025", 'Histórico26'!$A:$A, "<=31/09/2025")) -> 0 | U15: =IF(ISBLANK($A15), "", SUMIFS('Histórico26'!$C:$C, 'Histórico26'!$D:$D, $A15, 'Histórico26'!$A:$A, ">=01/10/2025", 'Histórico26'!$A:$A, "<=31/10/2025")) -> 0 | W15: =IF(ISBLANK($A15), "", SUMIFS('Histórico26'!$C:$C, 'Histórico26'!$D:$D, $A15, 'Histórico26'!$A:$A, ">=01/11/2025", 'Histórico26'!$A:$A, "<=30/11/2025")) -> 0 | Y15: =IF(ISBLANK($A15), "", SUMIFS('Histórico26'!$C:$C, 'Histórico26'!$D:$D, $A15, 'Histórico26'!$A:$A, ">=01/12/2025", 'Histórico26'!$A:$A, "<=31/12/2025")) -> 0 | Z15: =SUM(B15+D15+F15+H15+J15+L15+N15+P15+R15+T15+V15+X15) -> 0 | AA15: =SUM(C15,E15,G15,I15,K15,M15,O15,Q15,S15,U15,W15,Y15) -> 0
A16: Presentes | C16: =IF(ISBLANK($A16), "", SUMIFS('Histórico26'!$C:$C, 'Histórico26'!$D:$D, $A16, 'Histórico26'!$A:$A, ">=01/01/2026", 'Histórico26'!$A:$A, "<=31/01/2026")) -> 0 | E16: =IF(ISBLANK($A16), "", SUMIFS('Histórico26'!$C:$C, 'Histórico26'!$D:$D, $A16, 'Histórico26'!$A:$A, ">=01/02/2026", 'Histórico26'!$A:$A, "<=28/02/2026")) -> 0 | G16: =IF(ISBLANK($A16), "", SUMIFS('Histórico26'!$C:$C, 'Histórico26'!$D:$D, $A16, 'Histórico26'!$A:$A, ">=01/03/2026", 'Histórico26'!$A:$A, "<=31/03/2026")) -> 0 | I16: =IF(ISBLANK($A16), "", SUMIFS('Histórico26'!$C:$C, 'Histórico26'!$D:$D, $A16, 'Histórico26'!$A:$A, ">=01/04/2026", 'Histórico26'!$A:$A, "<=30/04/2026")) -> 0 | K16: =IF(ISBLANK($A16), "", SUMIFS('Histórico26'!$C:$C, 'Histórico26'!$D:$D, $A16, 'Histórico26'!$A:$A, ">=01/05/2026", 'Histórico26'!$A:$A, "<=31/05/2026")) -> 0 | M16: =IF(ISBLANK($A16), "", SUMIFS('Histórico26'!$C:$C, 'Histórico26'!$D:$D, $A16, 'Histórico26'!$A:$A, ">=01/06/2026", 'Histórico26'!$A:$A, "<=30/06/2026")) -> 0 | O16: =IF(ISBLANK($A16), "", SUMIFS('Histórico26'!$C:$C, 'Histórico26'!$D:$D, $A16, 'Histórico26'!$A:$A, ">=01/07/2026", 'Histórico26'!$A:$A, "<=31/07/2026")) -> 0 | Q16: =IF(ISBLANK($A16), "", SUMIFS('Histórico26'!$C:$C, 'Histórico26'!$D:$D, $A16, 'Histórico26'!$A:$A, ">=01/08/2025", 'Histórico26'!$A:$A, "<=31/08/2025")) -> 0 | S16: =IF(ISBLANK($A16), "", SUMIFS('Histórico26'!$C:$C, 'Histórico26'!$D:$D, $A16, 'Histórico26'!$A:$A, ">=01/09/2025", 'Histórico26'!$A:$A, "<=31/09/2025")) -> 0 | U16: =IF(ISBLANK($A16), "", SUMIFS('Histórico26'!$C:$C, 'Histórico26'!$D:$D, $A16, 'Histórico26'!$A:$A, ">=01/10/2025", 'Histórico26'!$A:$A, "<=31/10/2025")) -> 0 | W16: =IF(ISBLANK($A16), "", SUMIFS('Histórico26'!$C:$C, 'Histórico26'!$D:$D, $A16, 'Histórico26'!$A:$A, ">=01/11/2025", 'Histórico26'!$A:$A, "<=30/11/2025")) -> 0 | Y16: =IF(ISBLANK($A16), "", SUMIFS('Histórico26'!$C:$C, 'Histórico26'!$D:$D, $A16, 'Histórico26'!$A:$A, ">=01/12/2025", 'Histórico26'!$A:$A, "<=31/12/2025")) -> 0 | Z16: =SUM(B16+D16+F16+H16+J16+L16+N16+P16+R16+T16+V16+X16) -> 0 | AA16: =SUM(C16,E16,G16,I16,K16,M16,O16,Q16,S16,U16,W16,Y16) -> 0
A17: Outros (Saída) | C17: =IF(ISBLANK($A17), "", SUMIFS('Histórico26'!$C:$C, 'Histórico26'!$D:$D, $A17, 'Histórico26'!$A:$A, ">=01/01/2026", 'Histórico26'!$A:$A, "<=31/01/2026")) -> 0 | E17: =IF(ISBLANK($A17), "", SUMIFS('Histórico26'!$C:$C, 'Histórico26'!$D:$D, $A17, 'Histórico26'!$A:$A, ">=01/02/2026", 'Histórico26'!$A:$A, "<=28/02/2026")) -> 0 | G17: =IF(ISBLANK($A17), "", SUMIFS('Histórico26'!$C:$C, 'Histórico26'!$D:$D, $A17, 'Histórico26'!$A:$A, ">=01/03/2026", 'Histórico26'!$A:$A, "<=31/03/2026")) -> 0 | I17: =IF(ISBLANK($A17), "", SUMIFS('Histórico26'!$C:$C, 'Histórico26'!$D:$D, $A17, 'Histórico26'!$A:$A, ">=01/04/2026", 'Histórico26'!$A:$A, "<=30/04/2026")) -> 0 | K17: =IF(ISBLANK($A17), "", SUMIFS('Histórico26'!$C:$C, 'Histórico26'!$D:$D, $A17, 'Histórico26'!$A:$A, ">=01/05/2026", 'Histórico26'!$A:$A, "<=31/05/2026")) -> 0 | M17: =IF(ISBLANK($A17), "", SUMIFS('Histórico26'!$C:$C, 'Histórico26'!$D:$D, $A17, 'Histórico26'!$A:$A, ">=01/06/2026", 'Histórico26'!$A:$A, "<=30/06/2026")) -> 0 | O17: =IF(ISBLANK($A17), "", SUMIFS('Histórico26'!$C:$C, 'Histórico26'!$D:$D, $A17, 'Histórico26'!$A:$A, ">=01/07/2026", 'Histórico26'!$A:$A, "<=31/07/2026")) -> 0 | Q17: =IF(ISBLANK($A17), "", SUMIFS('Histórico26'!$C:$C, 'Histórico26'!$D:$D, $A17, 'Histórico26'!$A:$A, ">=01/08/2025", 'Histórico26'!$A:$A, "<=31/08/2025")) -> 0 | S17: =IF(ISBLANK($A17), "", SUMIFS('Histórico26'!$C:$C, 'Histórico26'!$D:$D, $A17, 'Histórico26'!$A:$A, ">=01/09/2025", 'Histórico26'!$A:$A, "<=31/09/2025")) -> 0 | U17: =IF(ISBLANK($A17), "", SUMIFS('Histórico26'!$C:$C, 'Histórico26'!$D:$D, $A17, 'Histórico26'!$A:$A, ">=01/10/2025", 'Histórico26'!$A:$A, "<=31/10/2025")) -> 0 | W17: =IF(ISBLANK($A17), "", SUMIFS('Histórico26'!$C:$C, 'Histórico26'!$D:$D, $A17, 'Histórico26'!$A:$A, ">=01/11/2025", 'Histórico26'!$A:$A, "<=30/11/2025")) -> 0 | Y17: =IF(ISBLANK($A17), "", SUMIFS('Histórico26'!$C:$C, 'Histórico26'!$D:$D, $A17, 'Histórico26'!$A:$A, ">=01/12/2025", 'Histórico26'!$A:$A, "<=31/12/2025")) -> 0 | Z17: =SUM(B17+D17+F17+H17+J17+L17+N17+P17+R17+T17+V17+X17) -> 0 | AA17: =SUM(C17,E17,G17,I17,K17,M17,O17,Q17,S17,U17,W17,Y17) -> 0
A18: Manutenção Casa | B18: 0 | C18: =IF(ISBLANK($A18), "", SUMIFS('Histórico26'!$C:$C, 'Histórico26'!$D:$D, $A18, 'Histórico26'!$A:$A, ">=01/01/2026", 'Histórico26'!$A:$A, "<=31/01/2026")) -> 0 | D18: 0 | E18: =IF(ISBLANK($A18), "", SUMIFS('Histórico26'!$C:$C, 'Histórico26'!$D:$D, $A18, 'Histórico26'!$A:$A, ">=01/02/2026", 'Histórico26'!$A:$A, "<=28/02/2026")) -> 0 | F18: 120 | G18: =IF(ISBLANK($A18), "", SUMIFS('Histórico26'!$C:$C, 'Histórico26'!$D:$D, $A18, 'Histórico26'!$A:$A, ">=01/03/2026", 'Histórico26'!$A:$A, "<=31/03/2026")) -> 0 | H18: 120 | I18: =IF(ISBLANK($A18), "", SUMIFS('Histórico26'!$C:$C, 'Histórico26'!$D:$D, $A18, 'Histórico26'!$A:$A, ">=01/04/2026", 'Histórico26'!$A:$A, "<=30/04/2026")) -> 0 | J18: 0 | K18: =IF(ISBLANK($A18), "", SUMIFS('Histórico26'!$C:$C, 'Histórico26'!$D:$D, $A18, 'Histórico26'!$A:$A, ">=01/05/2026", 'Histórico26'!$A:$A, "<=31/05/2026")) -> 0 | L18: 0 | M18: =IF(ISBLANK($A18), "", SUMIFS('Histórico26'!$C:$C, 'Histórico26'!$D:$D, $A18, 'Histórico26'!$A:$A, ">=01/06/2026", 'Histórico26'!$A:$A, "<=30/06/2026")) -> 0 | N18: 0 | O18: =IF(ISBLANK($A18), "", SUMIFS('Histórico26'!$C:$C, 'Histórico26'!$D:$D, $A18, 'Histórico26'!$A:$A, ">=01/07/2026", 'Histórico26'!$A:$A, "<=31/07/2026")) -> 0 | P18: 0 | Q18: =IF(ISBLANK($A18), "", SUMIFS('Histórico26'!$C:$C, 'Histórico26'!$D:$D, $A18, 'Histórico26'!$A:$A, ">=01/08/2025", 'Histórico26'!$A:$A, "<=31/08/2025")) -> 0 | R18: 0 | S18: =IF(ISBLANK($A18), "", SUMIFS('Histórico26'!$C:$C, 'Histórico26'!$D:$D, $A18, 'Histórico26'!$A:$A, ">=01/09/2025", 'Histórico26'!$A:$A, "<=31/09/2025")) -> 0 | T18: 0 | U18: =IF(ISBLANK($A18), "", SUMIFS('Histórico26'!$C:$C, 'Histórico26'!$D:$D, $A18, 'Histórico26'!$A:$A, ">=01/10/2025", 'Histórico26'!$A:$A, "<=31/10/2025")) -> 0 | V18: 0 | W18: =IF(ISBLANK($A18), "", SUMIFS('Histórico26'!$C:$C, 'Histórico26'!$D:$D, $A18, 'Histórico26'!$A:$A, ">=01/11/2025", 'Histórico26'!$A:$A, "<=30/11/2025")) -> 0 | X18: 0 | Y18: =IF(ISBLANK($A18), "", SUMIFS('Histórico26'!$C:$C, 'Histórico26'!$D:$D, $A18, 'Histórico26'!$A:$A, ">=01/12/2025", 'Histórico26'!$A:$A, "<=31/12/2025")) -> 0 | Z18: =SUM(B18+D18+F18+H18+J18+L18+N18+P18+R18+T18+V18+X18) -> 240 | AA18: =SUM(C18,E18,G18,I18,K18,M18,O18,Q18,S18,U18,W18,Y18) -> 0
A19: () DESPESAS | B19: =SUM(B20:B31) -> 0 | C19: =SUM(C20:C31) -> 0 | D19: =SUM(D20:D31) -> 0 | E19: =SUM(E20:E31) -> 1.31 | F19: =SUM(F20:F31) -> 0 | G19: =SUM(G20:G31) -> 0 | H19: =SUM(H20:H31) -> 0 | I19: =SUM(I20:I31) -> 0 | ... AA19: =SUM(AA20:AA31) -> 1.31
A20: Financiamento casa | C20: =IF(ISBLANK($A20), "", SUMIFS('Histórico26'!$C:$C, 'Histórico26'!$D:$D, $A20, 'Histórico26'!$A:$A, ">=01/01/2026", 'Histórico26'!$A:$A, "<=31/01/2026")) -> 0 | E20: =IF(ISBLANK($A20), "", SUMIFS('Histórico26'!$C:$C, 'Histórico26'!$D:$D, $A20, 'Histórico26'!$A:$A, ">=01/02/2026", 'Histórico26'!$A:$A, "<=28/02/2026")) -> 0 | G20: =IF(ISBLANK($A20), "", SUMIFS('Histórico26'!$C:$C, 'Histórico26'!$D:$D, $A20, 'Histórico26'!$A:$A, ">=01/03/2026", 'Histórico26'!$A:$A, "<=31/03/2026")) -> 0 | I20: =IF(ISBLANK($A20), "", SUMIFS('Histórico26'!$C:$C, 'Histórico26'!$D:$D, $A20, 'Histórico26'!$A:$A, ">=01/04/2026", 'Histórico26'!$A:$A, "<=30/04/2026")) -> 0 | K20: =IF(ISBLANK($A20), "", SUMIFS('Histórico26'!$C:$C, 'Histórico26'!$D:$D, $A20, 'Histórico26'!$A:$A, ">=01/05/2026", 'Histórico26'!$A:$A, "<=31/05/2026")) -> 0 | M20: =IF(ISBLANK($A20), "", SUMIFS('Histórico26'!$C:$C, 'Histórico26'!$D:$D, $A20, 'Histórico26'!$A:$A, ">=01/06/2026", 'Histórico26'!$A:$A, "<=30/06/2026")) -> 0 | O20: =IF(ISBLANK($A20), "", SUMIFS('Histórico26'!$C:$C, 'Histórico26'!$D:$D, $A20, 'Histórico26'!$A:$A, ">=01/07/2026", 'Histórico26'!$A:$A, "<=31/07/2026")) -> 0 | Q20: =IF(ISBLANK($A20), "", SUMIFS('Histórico26'!$C:$C, 'Histórico26'!$D:$D, $A20, 'Histórico26'!$A:$A, ">=01/08/2025", 'Histórico26'!$A:$A, "<=31/08/2025")) -> 0 | S20: =IF(ISBLANK($A20), "", SUMIFS('Histórico26'!$C:$C, 'Histórico26'!$D:$D, $A20, 'Histórico26'!$A:$A, ">=01/09/2025", 'Histórico26'!$A:$A, "<=31/09/2025")) -> 0 | U20: =IF(ISBLANK($A20), "", SUMIFS('Histórico26'!$C:$C, 'Histórico26'!$D:$D, $A20, 'Histórico26'!$A:$A, ">=01/10/2025", 'Histórico26'!$A:$A, "<=31/10/2025")) -> 0 | W20: =IF(ISBLANK($A20), "", SUMIFS('Histórico26'!$C:$C, 'Histórico26'!$D:$D, $A20, 'Histórico26'!$A:$A, ">=01/11/2025", 'Histórico26'!$A:$A, "<=30/11/2025")) -> 0 | Y20: =IF(ISBLANK($A20), "", SUMIFS('Histórico26'!$C:$C, 'Histórico26'!$D:$D, $A20, 'Histórico26'!$A:$A, ">=01/12/2025", 'Histórico26'!$A:$A, "<=31/12/2025")) -> 0 | Z20: =SUM(B20+D20+F20+H20+J20+L20+N20+P20+R20+T20+V20+X20) -> 0 | AA20: =SUM(C20,E20,G20,I20,K20,M20,O20,Q20,S20,U20,W20,Y20) -> 0
A21: Água | C21: =IF(ISBLANK($A21), "", SUMIFS('Histórico26'!$C:$C, 'Histórico26'!$D:$D, $A21, 'Histórico26'!$A:$A, ">=01/01/2026", 'Histórico26'!$A:$A, "<=31/01/2026")) -> 0 | E21: =IF(ISBLANK($A21), "", SUMIFS('Histórico26'!$C:$C, 'Histórico26'!$D:$D, $A21, 'Histórico26'!$A:$A, ">=01/02/2026", 'Histórico26'!$A:$A, "<=28/02/2026")) -> 0 | G21: =IF(ISBLANK($A21), "", SUMIFS('Histórico26'!$C:$C, 'Histórico26'!$D:$D, $A21, 'Histórico26'!$A:$A, ">=01/03/2026", 'Histórico26'!$A:$A, "<=31/03/2026")) -> 0 | I21: =IF(ISBLANK($A21), "", SUMIFS('Histórico26'!$C:$C, 'Histórico26'!$D:$D, $A21, 'Histórico26'!$A:$A, ">=01/04/2026", 'Histórico26'!$A:$A, "<=30/04/2026")) -> 0 | K21: =IF(ISBLANK($A21), "", SUMIFS('Histórico26'!$C:$C, 'Histórico26'!$D:$D, $A21, 'Histórico26'!$A:$A, ">=01/05/2026", 'Histórico26'!$A:$A, "<=31/05/2026")) -> 0 | M21: =IF(ISBLANK($A21), "", SUMIFS('Histórico26'!$C:$C, 'Histórico26'!$D:$D, $A21, 'Histórico26'!$A:$A, ">=01/06/2026", 'Histórico26'!$A:$A, "<=30/06/2026")) -> 0 | O21: =IF(ISBLANK($A21), "", SUMIFS('Histórico26'!$C:$C, 'Histórico26'!$D:$D, $A21, 'Histórico26'!$A:$A, ">=01/07/2026", 'Histórico26'!$A:$A, "<=31/07/2026")) -> 0 | Q21: =IF(ISBLANK($A21), "", SUMIFS('Histórico26'!$C:$C, 'Histórico26'!$D:$D, $A21, 'Histórico26'!$A:$A, ">=01/08/2025", 'Histórico26'!$A:$A, "<=31/08/2025")) -> 0 | S21: =IF(ISBLANK($A21), "", SUMIFS('Histórico26'!$C:$C, 'Histórico26'!$D:$D, $A21, 'Histórico26'!$A:$A, ">=01/09/2025", 'Histórico26'!$A:$A, "<=31/09/2025")) -> 0 | U21: =IF(ISBLANK($A21), "", SUMIFS('Histórico26'!$C:$C, 'Histórico26'!$D:$D, $A21, 'Histórico26'!$A:$A, ">=01/10/2025", 'Histórico26'!$A:$A, "<=31/10/2025")) -> 0 | W21: =IF(ISBLANK($A21), "", SUMIFS('Histórico26'!$C:$C, 'Histórico26'!$D:$D, $A21, 'Histórico26'!$A:$A, ">=01/11/2025", 'Histórico26'!$A:$A, "<=30/11/2025")) -> 0 | Y21: =IF(ISBLANK($A21), "", SUMIFS('Histórico26'!$C:$C, 'Histórico26'!$D:$D, $A21, 'Histórico26'!$A:$A, ">=01/12/2025", 'Histórico26'!$A:$A, "<=31/12/2025")) -> 0 | Z21: =SUM(B21+D21+F21+H21+J21+L21+N21+P21+R21+T21+V21+X21) -> 0 | AA21: =SUM(C21,E21,G21,I21,K21,M21,O21,Q21,S21,U21,W21,Y21) -> 0
A22: Energia | C22: =IF(ISBLANK($A22), "", SUMIFS('Histórico26'!$C:$C, 'Histórico26'!$D:$D, $A22, 'Histórico26'!$A:$A, ">=01/01/2026", 'Histórico26'!$A:$A, "<=31/01/2026")) -> 0 | E22: =IF(ISBLANK($A22), "", SUMIFS('Histórico26'!$C:$C, 'Histórico26'!$D:$D, $A22, 'Histórico26'!$A:$A, ">=01/02/2026", 'Histórico26'!$A:$A, "<=28/02/2026")) -> 0 | G22: =IF(ISBLANK($A22), "", SUMIFS('Histórico26'!$C:$C, 'Histórico26'!$D:$D, $A22, 'Histórico26'!$A:$A, ">=01/03/2026", 'Histórico26'!$A:$A, "<=31/03/2026")) -> 0 | I22: =IF(ISBLANK($A22), "", SUMIFS('Histórico26'!$C:$C, 'Histórico26'!$D:$D, $A22, 'Histórico26'!$A:$A, ">=01/04/2026", 'Histórico26'!$A:$A, "<=30/04/2026")) -> 0 | K22: =IF(ISBLANK($A22), "", SUMIFS('Histórico26'!$C:$C, 'Histórico26'!$D:$D, $A22, 'Histórico26'!$A:$A, ">=01/05/2026", 'Histórico26'!$A:$A, "<=31/05/2026")) -> 0 | M22: =IF(ISBLANK($A22), "", SUMIFS('Histórico26'!$C:$C, 'Histórico26'!$D:$D, $A22, 'Histórico26'!$A:$A, ">=01/06/2026", 'Histórico26'!$A:$A, "<=30/06/2026")) -> 0 | O22: =IF(ISBLANK($A22), "", SUMIFS('Histórico26'!$C:$C, 'Histórico26'!$D:$D, $A22, 'Histórico26'!$A:$A, ">=01/07/2026", 'Histórico26'!$A:$A, "<=31/07/2026")) -> 0 | Q22: =IF(ISBLANK($A22), "", SUMIFS('Histórico26'!$C:$C, 'Histórico26'!$D:$D, $A22, 'Histórico26'!$A:$A, ">=01/08/2025", 'Histórico26'!$A:$A, "<=31/08/2025")) -> 0 | S22: =IF(ISBLANK($A22), "", SUMIFS('Histórico26'!$C:$C, 'Histórico26'!$D:$D, $A22, 'Histórico26'!$A:$A, ">=01/09/2025", 'Histórico26'!$A:$A, "<=31/09/2025")) -> 0 | U22: =IF(ISBLANK($A22), "", SUMIFS('Histórico26'!$C:$C, 'Histórico26'!$D:$D, $A22, 'Histórico26'!$A:$A, ">=01/10/2025", 'Histórico26'!$A:$A, "<=31/10/2025")) -> 0 | W22: =IF(ISBLANK($A22), "", SUMIFS('Histórico26'!$C:$C, 'Histórico26'!$D:$D, $A22, 'Histórico26'!$A:$A, ">=01/11/2025", 'Histórico26'!$A:$A, "<=30/11/2025")) -> 0 | Y22: =IF(ISBLANK($A22), "", SUMIFS('Histórico26'!$C:$C, 'Histórico26'!$D:$D, $A22, 'Histórico26'!$A:$A, ">=01/12/2025", 'Histórico26'!$A:$A, "<=31/12/2025")) -> 0 | Z22: =SUM(B22+D22+F22+H22+J22+L22+N22+P22+R22+T22+V22+X22) -> 0 | AA22: =SUM(C22,E22,G22,I22,K22,M22,O22,Q22,S22,U22,W22,Y22) -> 0
A23: Internet / Recarga | C23: =IF(ISBLANK($A23), "", SUMIFS('Histórico26'!$C:$C, 'Histórico26'!$D:$D, $A23, 'Histórico26'!$A:$A, ">=01/01/2026", 'Histórico26'!$A:$A, "<=31/01/2026")) -> 0 | E23: =IF(ISBLANK($A23), "", SUMIFS('Histórico26'!$C:$C, 'Histórico26'!$D:$D, $A23, 'Histórico26'!$A:$A, ">=01/02/2026", 'Histórico26'!$A:$A, "<=28/02/2026")) -> 0 | G23: =IF(ISBLANK($A23), "", SUMIFS('Histórico26'!$C:$C, 'Histórico26'!$D:$D, $A23, 'Histórico26'!$A:$A, ">=01/03/2026", 'Histórico26'!$A:$A, "<=31/03/2026")) -> 0 | I23: =IF(ISBLANK($A23), "", SUMIFS('Histórico26'!$C:$C, 'Histórico26'!$D:$D, $A23, 'Histórico26'!$A:$A, ">=01/04/2026", 'Histórico26'!$A:$A, "<=30/04/2026")) -> 0 | K23: =IF(ISBLANK($A23), "", SUMIFS('Histórico26'!$C:$C, 'Histórico26'!$D:$D, $A23, 'Histórico26'!$A:$A, ">=01/05/2026", 'Histórico26'!$A:$A, "<=31/05/2026")) -> 0 | M23: =IF(ISBLANK($A23), "", SUMIFS('Histórico26'!$C:$C, 'Histórico26'!$D:$D, $A23, 'Histórico26'!$A:$A, ">=01/06/2026", 'Histórico26'!$A:$A, "<=30/06/2026")) -> 0 | O23: =IF(ISBLANK($A23), "", SUMIFS('Histórico26'!$C:$C, 'Histórico26'!$D:$D, $A23, 'Histórico26'!$A:$A, ">=01/07/2026", 'Histórico26'!$A:$A, "<=31/07/2026")) -> 0 | Q23: =IF(ISBLANK($A23), "", SUMIFS('Histórico26'!$C:$C, 'Histórico26'!$D:$D, $A23, 'Histórico26'!$A:$A, ">=01/08/2025", 'Histórico26'!$A:$A, "<=31/08/2025")) -> 0 | S23: =IF(ISBLANK($A23), "", SUMIFS('Histórico26'!$C:$C, 'Histórico26'!$D:$D, $A23, 'Histórico26'!$A:$A, ">=01/09/2025", 'Histórico26'!$A:$A, "<=31/09/2025")) -> 0 | U23: =IF(ISBLANK($A23), "", SUMIFS('Histórico26'!$C:$C, 'Histórico26'!$D:$D, $A23, 'Histórico26'!$A:$A, ">=01/10/2025", 'Histórico26'!$A:$A, "<=31/10/2025")) -> 0 | W23: =IF(ISBLANK($A23), "", SUMIFS('Histórico26'!$C:$C, 'Histórico26'!$D:$D, $A23, 'Histórico26'!$A:$A, ">=01/11/2025", 'Histórico26'!$A:$A, "<=30/11/2025")) -> 0 | Y23: =IF(ISBLANK($A23), "", SUMIFS('Histórico26'!$C:$C, 'Histórico26'!$D:$D, $A23, 'Histórico26'!$A:$A, ">=01/12/2025", 'Histórico26'!$A:$A, "<=31/12/2025")) -> 0 | Z23: =SUM(B23+D23+F23+H23+J23+L23+N23+P23+R23+T23+V23+X23) -> 0 | AA23: =SUM(C23,E23,G23,I23,K23,M23,O23,Q23,S23,U23,W23,Y23) -> 0
A24: Feira | C24: =IF(ISBLANK($A24), "", SUMIFS('Histórico26'!$C:$C, 'Histórico26'!$D:$D, $A24, 'Histórico26'!$A:$A, ">=01/01/2026", 'Histórico26'!$A:$A, "<=31/01/2026")) -> 0 | E24: =IF(ISBLANK($A24), "", SUMIFS('Histórico26'!$C:$C, 'Histórico26'!$D:$D, $A24, 'Histórico26'!$A:$A, ">=01/02/2026", 'Histórico26'!$A:$A, "<=28/02/2026")) -> 0 | G24: =IF(ISBLANK($A24), "", SUMIFS('Histórico26'!$C:$C, 'Histórico26'!$D:$D, $A24, 'Histórico26'!$A:$A, ">=01/03/2026", 'Histórico26'!$A:$A, "<=31/03/2026")) -> 0 | I24: =IF(ISBLANK($A24), "", SUMIFS('Histórico26'!$C:$C, 'Histórico26'!$D:$D, $A24, 'Histórico26'!$A:$A, ">=01/04/2026", 'Histórico26'!$A:$A, "<=30/04/2026")) -> 0 | K24: =IF(ISBLANK($A24), "", SUMIFS('Histórico26'!$C:$C, 'Histórico26'!$D:$D, $A24, 'Histórico26'!$A:$A, ">=01/05/2026", 'Histórico26'!$A:$A, "<=31/05/2026")) -> 0 | M24: =IF(ISBLANK($A24), "", SUMIFS('Histórico26'!$C:$C, 'Histórico26'!$D:$D, $A24, 'Histórico26'!$A:$A, ">=01/06/2026", 'Histórico26'!$A:$A, "<=30/06/2026")) -> 0 | O24: =IF(ISBLANK($A24), "", SUMIFS('Histórico26'!$C:$C, 'Histórico26'!$D:$D, $A24, 'Histórico26'!$A:$A, ">=01/07/2026", 'Histórico26'!$A:$A, "<=31/07/2026")) -> 0 | Q24: =IF(ISBLANK($A24), "", SUMIFS('Histórico26'!$C:$C, 'Histórico26'!$D:$D, $A24, 'Histórico26'!$A:$A, ">=01/08/2025", 'Histórico26'!$A:$A, "<=31/08/2025")) -> 0 | S24: =IF(ISBLANK($A24), "", SUMIFS('Histórico26'!$C:$C, 'Histórico26'!$D:$D, $A24, 'Histórico26'!$A:$A, ">=01/09/2025", 'Histórico26'!$A:$A, "<=31/09/2025")) -> 0 | U24: =IF(ISBLANK($A24), "", SUMIFS('Histórico26'!$C:$C, 'Histórico26'!$D:$D, $A24, 'Histórico26'!$A:$A, ">=01/10/2025", 'Histórico26'!$A:$A, "<=31/10/2025")) -> 0 | W24: =IF(ISBLANK($A24), "", SUMIFS('Histórico26'!$C:$C, 'Histórico26'!$D:$D, $A24, 'Histórico26'!$A:$A, ">=01/11/2025", 'Histórico26'!$A:$A, "<=30/11/2025")) -> 0 | Y24: =IF(ISBLANK($A24), "", SUMIFS('Histórico26'!$C:$C, 'Histórico26'!$D:$D, $A24, 'Histórico26'!$A:$A, ">=01/12/2025", 'Histórico26'!$A:$A, "<=31/12/2025")) -> 0 | Z24: =SUM(B24+D24+F24+H24+J24+L24+N24+P24+R24+T24+V24+X24) -> 0 | AA24: =SUM(C24,E24,G24,I24,K24,M24,O24,Q24,S24,U24,W24,Y24) -> 0
A25: Farmácia | C25: =IF(ISBLANK($A25), "", SUMIFS('Histórico26'!$C:$C, 'Histórico26'!$D:$D, $A25, 'Histórico26'!$A:$A, ">=01/01/2026", 'Histórico26'!$A:$A, "<=31/01/2026")) -> 0 | E25: =IF(ISBLANK($A25), "", SUMIFS('Histórico26'!$C:$C, 'Histórico26'!$D:$D, $A25, 'Histórico26'!$A:$A, ">=01/02/2026", 'Histórico26'!$A:$A, "<=28/02/2026")) -> 0 | G25: =IF(ISBLANK($A25), "", SUMIFS('Histórico26'!$C:$C, 'Histórico26'!$D:$D, $A25, 'Histórico26'!$A:$A, ">=01/03/2026", 'Histórico26'!$A:$A, "<=31/03/2026")) -> 0 | I25: =IF(ISBLANK($A25), "", SUMIFS('Histórico26'!$C:$C, 'Histórico26'!$D:$D, $A25, 'Histórico26'!$A:$A, ">=01/04/2026", 'Histórico26'!$A:$A, "<=30/04/2026")) -> 0 | K25: =IF(ISBLANK($A25), "", SUMIFS('Histórico26'!$C:$C, 'Histórico26'!$D:$D, $A25, 'Histórico26'!$A:$A, ">=01/05/2026", 'Histórico26'!$A:$A, "<=31/05/2026")) -> 0 | M25: =IF(ISBLANK($A25), "", SUMIFS('Histórico26'!$C:$C, 'Histórico26'!$D:$D, $A25, 'Histórico26'!$A:$A, ">=01/06/2026", 'Histórico26'!$A:$A, "<=30/06/2026")) -> 0 | O25: =IF(ISBLANK($A25), "", SUMIFS('Histórico26'!$C:$C, 'Histórico26'!$D:$D, $A25, 'Histórico26'!$A:$A, ">=01/07/2026", 'Histórico26'!$A:$A, "<=31/07/2026")) -> 0 | Q25: =IF(ISBLANK($A25), "", SUMIFS('Histórico26'!$C:$C, 'Histórico26'!$D:$D, $A25, 'Histórico26'!$A:$A, ">=01/08/2025", 'Histórico26'!$A:$A, "<=31/08/2025")) -> 0 | S25: =IF(ISBLANK($A25), "", SUMIFS('Histórico26'!$C:$C, 'Histórico26'!$D:$D, $A25, 'Histórico26'!$A:$A, ">=01/09/2025", 'Histórico26'!$A:$A, "<=31/09/2025")) -> 0 | U25: =IF(ISBLANK($A25), "", SUMIFS('Histórico26'!$C:$C, 'Histórico26'!$D:$D, $A25, 'Histórico26'!$A:$A, ">=01/10/2025", 'Histórico26'!$A:$A, "<=31/10/2025")) -> 0 | W25: =IF(ISBLANK($A25), "", SUMIFS('Histórico26'!$C:$C, 'Histórico26'!$D:$D, $A25, 'Histórico26'!$A:$A, ">=01/11/2025", 'Histórico26'!$A:$A, "<=30/11/2025")) -> 0 | Y25: =IF(ISBLANK($A25), "", SUMIFS('Histórico26'!$C:$C, 'Histórico26'!$D:$D, $A25, 'Histórico26'!$A:$A, ">=01/12/2025", 'Histórico26'!$A:$A, "<=31/12/2025")) -> 0 | Z25: =SUM(B25+D25+F25+H25+J25+L25+N25+P25+R25+T25+V25+X25) -> 0 | AA25: =SUM(C25,E25,G25,I25,K25,M25,O25,Q25,S25,U25,W25,Y25) -> 0
A26: Exames | C26: =IF(ISBLANK($A26), "", SUMIFS('Histórico26'!$C:$C, 'Histórico26'!$D:$D, $A26, 'Histórico26'!$A:$A, ">=01/01/2026", 'Histórico26'!$A:$A, "<=31/01/2026")) -> 0 | E26: =IF(ISBLANK($A26), "", SUMIFS('Histórico26'!$C:$C, 'Histórico26'!$D:$D, $A26, 'Histórico26'!$A:$A, ">=01/02/2026", 'Histórico26'!$A:$A, "<=28/02/2026")) -> 0 | G26: =IF(ISBLANK($A26), "", SUMIFS('Histórico26'!$C:$C, 'Histórico26'!$D:$D, $A26, 'Histórico26'!$A:$A, ">=01/03/2026", 'Histórico26'!$A:$A, "<=31/03/2026")) -> 0 | I26: =IF(ISBLANK($A26), "", SUMIFS('Histórico26'!$C:$C, 'Histórico26'!$D:$D, $A26, 'Histórico26'!$A:$A, ">=01/04/2026", 'Histórico26'!$A:$A, "<=30/04/2026")) -> 0 | K26: =IF(ISBLANK($A26), "", SUMIFS('Histórico26'!$C:$C, 'Histórico26'!$D:$D, $A26, 'Histórico26'!$A:$A, ">=01/05/2026", 'Histórico26'!$A:$A, "<=31/05/2026")) -> 0 | M26: =IF(ISBLANK($A26), "", SUMIFS('Histórico26'!$C:$C, 'Histórico26'!$D:$D, $A26, 'Histórico26'!$A:$A, ">=01/06/2026", 'Histórico26'!$A:$A, "<=30/06/2026")) -> 0 | O26: =IF(ISBLANK($A26), "", SUMIFS('Histórico26'!$C:$C, 'Histórico26'!$D:$D, $A26, 'Histórico26'!$A:$A, ">=01/07/2026", 'Histórico26'!$A:$A, "<=31/07/2026")) -> 0 | Q26: =IF(ISBLANK($A26), "", SUMIFS('Histórico26'!$C:$C, 'Histórico26'!$D:$D, $A26, 'Histórico26'!$A:$A, ">=01/08/2025", 'Histórico26'!$A:$A, "<=31/08/2025")) -> 0 | S26: =IF(ISBLANK($A26), "", SUMIFS('Histórico26'!$C:$C, 'Histórico26'!$D:$D, $A26, 'Histórico26'!$A:$A, ">=01/09/2025", 'Histórico26'!$A:$A, "<=31/09/2025")) -> 0 | U26: =IF(ISBLANK($A26), "", SUMIFS('Histórico26'!$C:$C, 'Histórico26'!$D:$D, $A26, 'Histórico26'!$A:$A, ">=01/10/2025", 'Histórico26'!$A:$A, "<=31/10/2025")) -> 0 | W26: =IF(ISBLANK($A26), "", SUMIFS('Histórico26'!$C:$C, 'Histórico26'!$D:$D, $A26, 'Histórico26'!$A:$A, ">=01/11/2025", 'Histórico26'!$A:$A, "<=30/11/2025")) -> 0 | Y26: =IF(ISBLANK($A26), "", SUMIFS('Histórico26'!$C:$C, 'Histórico26'!$D:$D, $A26, 'Histórico26'!$A:$A, ">=01/12/2025", 'Histórico26'!$A:$A, "<=31/12/2025")) -> 0 | Z26: =SUM(B26+D26+F26+H26+J26+L26+N26+P26+R26+T26+V26+X26) -> 0 | AA26: =SUM(C26,E26,G26,I26,K26,M26,O26,Q26,S26,U26,W26,Y26) -> 0
A27: Academia | C27: =IF(ISBLANK($A27), "", SUMIFS('Histórico26'!$C:$C, 'Histórico26'!$D:$D, $A27, 'Histórico26'!$A:$A, ">=01/01/2026", 'Histórico26'!$A:$A, "<=31/01/2026")) -> 0 | E27: =IF(ISBLANK($A27), "", SUMIFS('Histórico26'!$C:$C, 'Histórico26'!$D:$D, $A27, 'Histórico26'!$A:$A, ">=01/02/2026", 'Histórico26'!$A:$A, "<=28/02/2026")) -> 0 | G27: =IF(ISBLANK($A27), "", SUMIFS('Histórico26'!$C:$C, 'Histórico26'!$D:$D, $A27, 'Histórico26'!$A:$A, ">=01/03/2026", 'Histórico26'!$A:$A, "<=31/03/2026")) -> 0 | I27: =IF(ISBLANK($A27), "", SUMIFS('Histórico26'!$C:$C, 'Histórico26'!$D:$D, $A27, 'Histórico26'!$A:$A, ">=01/04/2026", 'Histórico26'!$A:$A, "<=30/04/2026")) -> 0 | K27: =IF(ISBLANK($A27), "", SUMIFS('Histórico26'!$C:$C, 'Histórico26'!$D:$D, $A27, 'Histórico26'!$A:$A, ">=01/05/2026", 'Histórico26'!$A:$A, "<=31/05/2026")) -> 0 | M27: =IF(ISBLANK($A27), "", SUMIFS('Histórico26'!$C:$C, 'Histórico26'!$D:$D, $A27, 'Histórico26'!$A:$A, ">=01/06/2026", 'Histórico26'!$A:$A, "<=30/06/2026")) -> 0 | O27: =IF(ISBLANK($A27), "", SUMIFS('Histórico26'!$C:$C, 'Histórico26'!$D:$D, $A27, 'Histórico26'!$A:$A, ">=01/07/2026", 'Histórico26'!$A:$A, "<=31/07/2026")) -> 0 | Q27: =IF(ISBLANK($A27), "", SUMIFS('Histórico26'!$C:$C, 'Histórico26'!$D:$D, $A27, 'Histórico26'!$A:$A, ">=01/08/2025", 'Histórico26'!$A:$A, "<=31/08/2025")) -> 0 | S27: =IF(ISBLANK($A27), "", SUMIFS('Histórico26'!$C:$C, 'Histórico26'!$D:$D, $A27, 'Histórico26'!$A:$A, ">=01/09/2025", 'Histórico26'!$A:$A, "<=31/09/2025")) -> 0 | U27: =IF(ISBLANK($A27), "", SUMIFS('Histórico26'!$C:$C, 'Histórico26'!$D:$D, $A27, 'Histórico26'!$A:$A, ">=01/10/2025", 'Histórico26'!$A:$A, "<=31/10/2025")) -> 0 | W27: =IF(ISBLANK($A27), "", SUMIFS('Histórico26'!$C:$C, 'Histórico26'!$D:$D, $A27, 'Histórico26'!$A:$A, ">=01/11/2025", 'Histórico26'!$A:$A, "<=30/11/2025")) -> 0 | Y27: =IF(ISBLANK($A27), "", SUMIFS('Histórico26'!$C:$C, 'Histórico26'!$D:$D, $A27, 'Histórico26'!$A:$A, ">=01/12/2025", 'Histórico26'!$A:$A, "<=31/12/2025")) -> 0 | Z27: =SUM(B27+D27+F27+H27+J27+L27+N27+P27+R27+T27+V27+X27) -> 0 | AA27: =SUM(C27,E27,G27,I27,K27,M27,O27,Q27,S27,U27,W27,Y27) -> 0
A28: Corte de cabelo | C28: =IF(ISBLANK($A28), "", SUMIFS('Histórico26'!$C:$C, 'Histórico26'!$D:$D, $A28, 'Histórico26'!$A:$A, ">=01/01/2026", 'Histórico26'!$A:$A, "<=31/01/2026")) -> 0 | E28: =IF(ISBLANK($A28), "", SUMIFS('Histórico26'!$C:$C, 'Histórico26'!$D:$D, $A28, 'Histórico26'!$A:$A, ">=01/02/2026", 'Histórico26'!$A:$A, "<=28/02/2026")) -> 0 | G28: =IF(ISBLANK($A28), "", SUMIFS('Histórico26'!$C:$C, 'Histórico26'!$D:$D, $A28, 'Histórico26'!$A:$A, ">=01/03/2026", 'Histórico26'!$A:$A, "<=31/03/2026")) -> 0 | I28: =IF(ISBLANK($A28), "", SUMIFS('Histórico26'!$C:$C, 'Histórico26'!$D:$D, $A28, 'Histórico26'!$A:$A, ">=01/04/2026", 'Histórico26'!$A:$A, "<=30/04/2026")) -> 0 | K28: =IF(ISBLANK($A28), "", SUMIFS('Histórico26'!$C:$C, 'Histórico26'!$D:$D, $A28, 'Histórico26'!$A:$A, ">=01/05/2026", 'Histórico26'!$A:$A, "<=31/05/2026")) -> 0 | M28: =IF(ISBLANK($A28), "", SUMIFS('Histórico26'!$C:$C, 'Histórico26'!$D:$D, $A28, 'Histórico26'!$A:$A, ">=01/06/2026", 'Histórico26'!$A:$A, "<=30/06/2026")) -> 0 | O28: =IF(ISBLANK($A28), "", SUMIFS('Histórico26'!$C:$C, 'Histórico26'!$D:$D, $A28, 'Histórico26'!$A:$A, ">=01/07/2026", 'Histórico26'!$A:$A, "<=31/07/2026")) -> 0 | Q28: =IF(ISBLANK($A28), "", SUMIFS('Histórico26'!$C:$C, 'Histórico26'!$D:$D, $A28, 'Histórico26'!$A:$A, ">=01/08/2025", 'Histórico26'!$A:$A, "<=31/08/2025")) -> 0 | S28: =IF(ISBLANK($A28), "", SUMIFS('Histórico26'!$C:$C, 'Histórico26'!$D:$D, $A28, 'Histórico26'!$A:$A, ">=01/09/2025", 'Histórico26'!$A:$A, "<=31/09/2025")) -> 0 | U28: =IF(ISBLANK($A28), "", SUMIFS('Histórico26'!$C:$C, 'Histórico26'!$D:$D, $A28, 'Histórico26'!$A:$A, ">=01/10/2025", 'Histórico26'!$A:$A, "<=31/10/2025")) -> 0 | W28: =IF(ISBLANK($A28), "", SUMIFS('Histórico26'!$C:$C, 'Histórico26'!$D:$D, $A28, 'Histórico26'!$A:$A, ">=01/11/2025", 'Histórico26'!$A:$A, "<=30/11/2025")) -> 0 | Y28: =IF(ISBLANK($A28), "", SUMIFS('Histórico26'!$C:$C, 'Histórico26'!$D:$D, $A28, 'Histórico26'!$A:$A, ">=01/12/2025", 'Histórico26'!$A:$A, "<=31/12/2025")) -> 0 | Z28: =SUM(B28+D28+F28+H28+J28+L28+N28+P28+R28+T28+V28+X28) -> 0 | AA28: =SUM(C28,E28,G28,I28,K28,M28,O28,Q28,S28,U28,W28,Y28) -> 0
A29: Consórcio moto | C29: =IF(ISBLANK($A29), "", SUMIFS('Histórico26'!$C:$C, 'Histórico26'!$D:$D, $A29, 'Histórico26'!$A:$A, ">=01/01/2026", 'Histórico26'!$A:$A, "<=31/01/2026")) -> 0 | E29: =IF(ISBLANK($A29), "", SUMIFS('Histórico26'!$C:$C, 'Histórico26'!$D:$D, $A29, 'Histórico26'!$A:$A, ">=01/02/2026", 'Histórico26'!$A:$A, "<=28/02/2026")) -> 0 | G29: =IF(ISBLANK($A29), "", SUMIFS('Histórico26'!$C:$C, 'Histórico26'!$D:$D, $A29, 'Histórico26'!$A:$A, ">=01/03/2026", 'Histórico26'!$A:$A, "<=31/03/2026")) -> 0 | I29: =IF(ISBLANK($A29), "", SUMIFS('Histórico26'!$C:$C, 'Histórico26'!$D:$D, $A29, 'Histórico26'!$A:$A, ">=01/04/2026", 'Histórico26'!$A:$A, "<=30/04/2026")) -> 0 | K29: =IF(ISBLANK($A29), "", SUMIFS('Histórico26'!$C:$C, 'Histórico26'!$D:$D, $A29, 'Histórico26'!$A:$A, ">=01/05/2026", 'Histórico26'!$A:$A, "<=31/05/2026")) -> 0 | M29: =IF(ISBLANK($A29), "", SUMIFS('Histórico26'!$C:$C, 'Histórico26'!$D:$D, $A29, 'Histórico26'!$A:$A, ">=01/06/2026", 'Histórico26'!$A:$A, "<=30/06/2026")) -> 0 | O29: =IF(ISBLANK($A29), "", SUMIFS('Histórico26'!$C:$C, 'Histórico26'!$D:$D, $A29, 'Histórico26'!$A:$A, ">=01/07/2026", 'Histórico26'!$A:$A, "<=31/07/2026")) -> 0 | Q29: =IF(ISBLANK($A29), "", SUMIFS('Histórico26'!$C:$C, 'Histórico26'!$D:$D, $A29, 'Histórico26'!$A:$A, ">=01/08/2025", 'Histórico26'!$A:$A, "<=31/08/2025")) -> 0 | S29: =IF(ISBLANK($A29), "", SUMIFS('Histórico26'!$C:$C, 'Histórico26'!$D:$D, $A29, 'Histórico26'!$A:$A, ">=01/09/2025", 'Histórico26'!$A:$A, "<=31/09/2025")) -> 0 | U29: =IF(ISBLANK($A29), "", SUMIFS('Histórico26'!$C:$C, 'Histórico26'!$D:$D, $A29, 'Histórico26'!$A:$A, ">=01/10/2025", 'Histórico26'!$A:$A, "<=31/10/2025")) -> 0 | W29: =IF(ISBLANK($A29), "", SUMIFS('Histórico26'!$C:$C, 'Histórico26'!$D:$D, $A29, 'Histórico26'!$A:$A, ">=01/11/2025", 'Histórico26'!$A:$A, "<=30/11/2025")) -> 0 | Y29: =IF(ISBLANK($A29), "", SUMIFS('Histórico26'!$C:$C, 'Histórico26'!$D:$D, $A29, 'Histórico26'!$A:$A, ">=01/12/2025", 'Histórico26'!$A:$A, "<=31/12/2025")) -> 0 | Z29: =SUM(B29+D29+F29+H29+J29+L29+N29+P29+R29+T29+V29+X29) -> 0 | AA29: =SUM(C29,E29,G29,I29,K29,M29,O29,Q29,S29,U29,W29,Y29) -> 0
A30: Estudos | C30: =IF(ISBLANK($A30), "", SUMIFS('Histórico26'!$C:$C, 'Histórico26'!$D:$D, $A30, 'Histórico26'!$A:$A, ">=01/01/2026", 'Histórico26'!$A:$A, "<=31/01/2026")) -> 0 | E30: =IF(ISBLANK($A30), "", SUMIFS('Histórico26'!$C:$C, 'Histórico26'!$D:$D, $A30, 'Histórico26'!$A:$A, ">=01/02/2026", 'Histórico26'!$A:$A, "<=28/02/2026")) -> 0 | G30: =IF(ISBLANK($A30), "", SUMIFS('Histórico26'!$C:$C, 'Histórico26'!$D:$D, $A30, 'Histórico26'!$A:$A, ">=01/03/2026", 'Histórico26'!$A:$A, "<=31/03/2026")) -> 0 | I30: =IF(ISBLANK($A30), "", SUMIFS('Histórico26'!$C:$C, 'Histórico26'!$D:$D, $A30, 'Histórico26'!$A:$A, ">=01/04/2026", 'Histórico26'!$A:$A, "<=30/04/2026")) -> 0 | K30: =IF(ISBLANK($A30), "", SUMIFS('Histórico26'!$C:$C, 'Histórico26'!$D:$D, $A30, 'Histórico26'!$A:$A, ">=01/05/2026", 'Histórico26'!$A:$A, "<=31/05/2026")) -> 0 | M30: =IF(ISBLANK($A30), "", SUMIFS('Histórico26'!$C:$C, 'Histórico26'!$D:$D, $A30, 'Histórico26'!$A:$A, ">=01/06/2026", 'Histórico26'!$A:$A, "<=30/06/2026")) -> 0 | O30: =IF(ISBLANK($A30), "", SUMIFS('Histórico26'!$C:$C, 'Histórico26'!$D:$D, $A30, 'Histórico26'!$A:$A, ">=01/07/2026", 'Histórico26'!$A:$A, "<=31/07/2026")) -> 0 | Q30: =IF(ISBLANK($A30), "", SUMIFS('Histórico26'!$C:$C, 'Histórico26'!$D:$D, $A30, 'Histórico26'!$A:$A, ">=01/08/2025", 'Histórico26'!$A:$A, "<=31/08/2025")) -> 0 | S30: =IF(ISBLANK($A30), "", SUMIFS('Histórico26'!$C:$C, 'Histórico26'!$D:$D, $A30, 'Histórico26'!$A:$A, ">=01/09/2025", 'Histórico26'!$A:$A, "<=31/09/2025")) -> 0 | U30: =IF(ISBLANK($A30), "", SUMIFS('Histórico26'!$C:$C, 'Histórico26'!$D:$D, $A30, 'Histórico26'!$A:$A, ">=01/10/2025", 'Histórico26'!$A:$A, "<=31/10/2025")) -> 0 | W30: =IF(ISBLANK($A30), "", SUMIFS('Histórico26'!$C:$C, 'Histórico26'!$D:$D, $A30, 'Histórico26'!$A:$A, ">=01/11/2025", 'Histórico26'!$A:$A, "<=30/11/2025")) -> 0 | Y30: =IF(ISBLANK($A30), "", SUMIFS('Histórico26'!$C:$C, 'Histórico26'!$D:$D, $A30, 'Histórico26'!$A:$A, ">=01/12/2025", 'Histórico26'!$A:$A, "<=31/12/2025")) -> 0 | Z30: =SUM(B30+D30+F30+H30+J30+L30+N30+P30+R30+T30+V30+X30) -> 0 | AA30: =SUM(C30,E30,G30,I30,K30,M30,O30,Q30,S30,U30,W30,Y30) -> 0
A31: Investimento (Saída) | C31: =IF(ISBLANK($A31), "", SUMIFS('Histórico26'!$C:$C, 'Histórico26'!$D:$D, $A31, 'Histórico26'!$A:$A, ">=01/01/2026", 'Histórico26'!$A:$A, "<=31/01/2026")) -> 0 | E31: =IF(ISBLANK($A31), "", SUMIFS('Histórico26'!$C:$C, 'Histórico26'!$D:$D, $A31, 'Histórico26'!$A:$A, ">=01/02/2026", 'Histórico26'!$A:$A, "<=28/02/2026")) + 1.31 -> 1.31 | G31: =IF(ISBLANK($A31), "", SUMIFS('Histórico26'!$C:$C, 'Histórico26'!$D:$D, $A31, 'Histórico26'!$A:$A, ">=01/03/2026", 'Histórico26'!$A:$A, "<=31/03/2026")) -> 0 | I31: =IF(ISBLANK($A31), "", SUMIFS('Histórico26'!$C:$C, 'Histórico26'!$D:$D, $A31, 'Histórico26'!$A:$A, ">=01/04/2026", 'Histórico26'!$A:$A, "<=30/04/2026")) -> 0 | K31: =IF(ISBLANK($A31), "", SUMIFS('Histórico26'!$C:$C, 'Histórico26'!$D:$D, $A31, 'Histórico26'!$A:$A, ">=01/05/2026", 'Histórico26'!$A:$A, "<=31/05/2026")) -> 0 | M31: =IF(ISBLANK($A31), "", SUMIFS('Histórico26'!$C:$C, 'Histórico26'!$D:$D, $A31, 'Histórico26'!$A:$A, ">=01/06/2026", 'Histórico26'!$A:$A, "<=30/06/2026")) -> 0 | O31: =IF(ISBLANK($A31), "", SUMIFS('Histórico26'!$C:$C, 'Histórico26'!$D:$D, $A31, 'Histórico26'!$A:$A, ">=01/07/2026", 'Histórico26'!$A:$A, "<=31/07/2026")) -> 0 | Q31: =IF(ISBLANK($A31), "", SUMIFS('Histórico26'!$C:$C, 'Histórico26'!$D:$D, $A31, 'Histórico26'!$A:$A, ">=01/08/2025", 'Histórico26'!$A:$A, "<=31/08/2025")) -> 0 | S31: =IF(ISBLANK($A31), "", SUMIFS('Histórico26'!$C:$C, 'Histórico26'!$D:$D, $A31, 'Histórico26'!$A:$A, ">=01/09/2025", 'Histórico26'!$A:$A, "<=31/09/2025")) -> 0 | U31: =IF(ISBLANK($A31), "", SUMIFS('Histórico26'!$C:$C, 'Histórico26'!$D:$D, $A31, 'Histórico26'!$A:$A, ">=01/10/2025", 'Histórico26'!$A:$A, "<=31/10/2025")) -> 0 | W31: =IF(ISBLANK($A31), "", SUMIFS('Histórico26'!$C:$C, 'Histórico26'!$D:$D, $A31, 'Histórico26'!$A:$A, ">=01/11/2025", 'Histórico26'!$A:$A, "<=30/11/2025")) -> 0 | Y31: =IF(ISBLANK($A31), "", SUMIFS('Histórico26'!$C:$C, 'Histórico26'!$D:$D, $A31, 'Histórico26'!$A:$A, ">=01/12/2025", 'Histórico26'!$A:$A, "<=31/12/2025")) -> 0 | Z31: =SUM(B31+D31+F31+H31+J31+L31+N31+P31+R31+T31+V31+X31) -> 0 | AA31: =SUM(C31,E31,G31,I31,K31,M31,O31,Q31,S31,U31,W31,Y31) -> 1.31

Sheet Histórico26
A1: Data | B1: Descrição | C1: Valor | D1: Categoria
A2: =Extrato26!A2 -> 46063 | B2: =Extrato26!B2 -> 10 | C2: =Extrato26!C2 -> TESTE | D2: Pró-labore
A3: =Extrato26!A3 | B3: =Extrato26!B3 | C3: =Extrato26!C3 | D3: Salário
A4: =Extrato26!A4 | B4: =Extrato26!B4 | C4: =Extrato26!C4 | D4: Outros (Entrada)
A5: =Extrato26!A5 | B5: =Extrato26!B5 | C5: =Extrato26!C5 | D5: Outros (Entrada)
A6: =Extrato26!A6 | B6: =Extrato26!B6 | C6: =Extrato26!C6 | D6: Outros (Entrada)
A7: =Extrato26!A7 | B7: =Extrato26!B7 | C7: =Extrato26!C7 | D7: Academia
A8: =Extrato26!A8 | B8: =Extrato26!B8 | C8: =Extrato26!C8 | D8: Outros (Saída)
A9: =Extrato26!A9 | B9: =Extrato26!B9 | C9: =Extrato26!C9 | D9: Internet / Recarga
A10: =Extrato26!A10 | B10: =Extrato26!B10 | C10: =Extrato26!C10 | D10: Internet / Recarga
A11: =Extrato26!A11 | B11: =Extrato26!B11 | C11: =Extrato26!C11 | D11: Energia
A12: =Extrato26!A12 | B12: =Extrato26!B12 | C12: =Extrato26!C12 | D12: Outros (Saída)
A13: =Extrato26!A13 | B13: =Extrato26!B13 | C13: =Extrato26!C13
A14: =Extrato26!A14 | B14: =Extrato26!B14 | C14: =Extrato26!C14
A15: =Extrato26!A15 | B15: =Extrato26!B15 | C15: =Extrato26!C15
A16: =Extrato26!A16 | B16: =Extrato26!B16 | C16: =Extrato26!C16
A17: =Extrato26!A17 | B17: =Extrato26!B17 | C17: =Extrato26!C17
A18: =Extrato26!A18 | B18: =Extrato26!B18 | C18: =Extrato26!C18
A19: =Extrato26!A19 | B19: =Extrato26!B19 | C19: =Extrato26!C19
A20: =Extrato26!A20 | B20: =Extrato26!B20 | C20: =Extrato26!C20
A21: =Extrato26!A21 | B21: =Extrato26!B21 | C21: =Extrato26!C21
A22: =Extrato26!A22 | B22: =Extrato26!B22 | C22: =Extrato26!C22
A23: =Extrato26!A23 | B23: =Extrato26!B23 | C23: =Extrato26!C23
A24: =Extrato26!A24 | B24: =Extrato26!B24 | C24: =Extrato26!C24
... A352: =Extrato26!A352 | B352: =Extrato26!B352 | C352: =Extrato26!C352
B353: =Extrato26!B353 | C353: =Extrato26!C353
B354: =Extrato26!B354 | C354: =Extrato26!C354
B355: =Extrato26!B355 | C355: =Extrato26!C355
B356: =Extrato26!B356 | C356: =Extrato26!C356

Sheet Extrato26
A1: Data | B1: Valor | C1: Identificador | D1: Descrição
A2: 46063 | B2: 10 | C2: TESTE | D2: TESTE
